address_book_vad/__init__.py
address_book_vad/main.py
address_book_vad-1.0.1.dist-info/LICENSE
address_book_vad-1.0.1.dist-info/METADATA
address_book_vad-1.0.1.dist-info/WHEEL
address_book_vad-1.0.1.dist-info/entry_points.txt
address_book_vad-1.0.1.dist-info/top_level.txt
address_book_vad-1.0.1.dist-info/RECORD
